{"cameraMode":{"drawMode":0,"name":"Shaded","section":"Shading Mode"},"sceneLighting":false,"audioPlay":false,"sceneViewState":{"m_AlwaysRefresh":false,"showFog":true,"showSkybox":false,"showFlares":true,"showImageEffects":true,"showParticleSystems":true,"showVisualEffectGraphs":true,"m_FxEnabled":true},"in2DMode":false,"pivot":{"x":0.0,"y":1.2734296321868897,"z":0.730785608291626},"rotation":{"x":0.0023276223801076414,"y":-0.9216688871383667,"z":0.005529939197003841,"w":0.3879362940788269},"size":3.975940704345703,"orthographic":false}